{
  "project_info": {
    "project_number": "1094065018592",
    "firebase_url": "https://farmingequipmentuser-7ede4.firebaseio.com",
    "project_id": "farmingequipmentuser-7ede4",
    "storage_bucket": "farmingequipmentuser-7ede4.appspot.com"
  },
  "client": [
    {
      "client_info": {
        "mobilesdk_app_id": "1:1094065018592:android:f77fc3c43beee7c7",
        "android_client_info": {
          "package_name": "virtuosonetsoft.pagingoffline"
        }
      },
      "oauth_client": [
        {
          "client_id": "1094065018592-3qi9afeavrv8e63a6bvrsv79r9r0bvgs.apps.googleusercontent.com",
          "client_type": 3
        }
      ],
      "api_key": [
        {
          "current_key": "AIzaSyAzQG6Bc_LdVg_rI3b6mYIdQKp7QvP1EsE"
        }
      ],
      "services": {
        "analytics_service": {
          "status": 1
        },
        "appinvite_service": {
          "status": 1,
          "other_platform_oauth_client": []
        },
        "ads_service": {
          "status": 2
        }
      }
    }
  ],
  "configuration_version": "1"
}